domcmc/__init__.py
domcmc/fst_tools.py
domcmc-2.1.5.dist-info/LICENSE.txt
domcmc-2.1.5.dist-info/METADATA
domcmc-2.1.5.dist-info/WHEEL
domcmc-2.1.5.dist-info/top_level.txt
domcmc-2.1.5.dist-info/RECORD
