Metadata-Version: 2.1
Name: domcmc
Version: 2.1.5
Summary: dominik's tools for reading fst files
Home-page: https://gitlab.science.gc.ca/dja001/domcmc
Author: Dominik Jacques
Author-email: dominik.jacques@gmail.com
License: MIT
Requires-Python: >=3
License-File: LICENSE.txt
Requires-Dist: numpy
